cybarpass-2.6.dist-info/METADATA
cybarpass-2.6.dist-info/WHEEL
cybarpass-2.6.dist-info/licenses/LICENSE
cybarpass/__init__.py
cybarpass/__main__.py
cybarpass/__runner.py
cybarpass/app.py
cybarpass/passgen.py
cybarpass/words
cybarpass-2.6.dist-info/RECORD
