Metadata-Version: 2.1
Name: cybarpass
Version: 2.6
Summary: Minimalistic Passphrase Generation script with GUI
Home-page: https://pass.cybar.dev
Author-Email: cybardev <sheikh@cybar.dev>
Classifier: Programming Language :: Python :: 3
Classifier: License :: OSI Approved :: GNU General Public License v3 or later (GPLv3+)
Classifier: Operating System :: OS Independent
Project-URL: Homepage, https://pass.cybar.dev
Project-URL: Repository, https://github.com/cybardev/cybarpass.git
Project-URL: Documentation, https://github.com/cybardev/CybarPass/blob/main/README.md
Requires-Python: >=3.9
